docums/__init__.py
docums/__main__.py
docums/exceptions.py
docums/localization.py
docums/plugins.py
docums/theme.py
docums/commands/__init__.py
docums/commands/babel.py
docums/commands/build.py
docums/commands/gh_deploy.py
docums/commands/new.py
docums/commands/serve.py
docums/commands/setup.py
docums/config/__init__.py
docums/config/base.py
docums/config/config_options.py
docums/config/defaults.py
docums/contrib/__init__.py
docums/contrib/search/__init__.py
docums/contrib/search/prebuild-index.js
docums/contrib/search/search_index.py
docums/contrib/search/lunr-language/lunr.ar.js
docums/contrib/search/lunr-language/lunr.da.js
docums/contrib/search/lunr-language/lunr.de.js
docums/contrib/search/lunr-language/lunr.du.js
docums/contrib/search/lunr-language/lunr.es.js
docums/contrib/search/lunr-language/lunr.fi.js
docums/contrib/search/lunr-language/lunr.fr.js
docums/contrib/search/lunr-language/lunr.hu.js
docums/contrib/search/lunr-language/lunr.it.js
docums/contrib/search/lunr-language/lunr.ja.js
docums/contrib/search/lunr-language/lunr.jp.js
docums/contrib/search/lunr-language/lunr.multi.js
docums/contrib/search/lunr-language/lunr.nl.js
docums/contrib/search/lunr-language/lunr.no.js
docums/contrib/search/lunr-language/lunr.pt.js
docums/contrib/search/lunr-language/lunr.ro.js
docums/contrib/search/lunr-language/lunr.ru.js
docums/contrib/search/lunr-language/lunr.stemmer.support.js
docums/contrib/search/lunr-language/lunr.sv.js
docums/contrib/search/lunr-language/lunr.th.js
docums/contrib/search/lunr-language/lunr.tr.js
docums/contrib/search/lunr-language/lunr.vi.js
docums/contrib/search/lunr-language/tinyseg.js
docums/contrib/search/templates/search/lunr.js
docums/contrib/search/templates/search/main.js
docums/contrib/search/templates/search/worker.js
docums/livereload/__init__.py
docums/structure/__init__.py
docums/structure/files.py
docums/structure/nav.py
docums/structure/pages.py
docums/structure/toc.py
docums/templates/sitemap.xml
docums/themes/__init__.py
docums-1.3.1.dist-info/LICENSE
docums-1.3.1.dist-info/METADATA
docums-1.3.1.dist-info/WHEEL
docums-1.3.1.dist-info/entry_points.txt
docums-1.3.1.dist-info/top_level.txt
docums-1.3.1.dist-info/RECORD
